Workbook

Sheet Read Me
A1: Workbook Guide
A2: Purpose, structure, definitions and controls
A4: Purpose | B4: Consolidated professional analysis of Mercado Pago account activity for April–August 2026.
A5: Coverage | B5: Five unique monthly statements: April, May, June, July and August 2026.
A6: Duplicate handling | B6: MercadoPago 4.pdf is a duplicate of the June statement and contributes no additional transactions.
A7: Transaction grain | B7: One row per unique operation ID.
A8: Amount convention | B8: Positive = inflow; negative = outflow.
A9: Balance | B9: Running account balance reported after each operation.
A10: Category logic | B10: Analytical classification based on the source description; it does not replace accounting treatment.
A11: Transfers | B11: Transfers to/from the account holder are kept separate from income/consumption.
A12: Credit card | B12: Card settlement is separated because the underlying purchases may belong to an earlier period.
A13: Judicial holds | B13: Court-ordered holds are kept separate from ordinary spending.
A14: Source fidelity | B14: April and May were transcribed from statement text supplied in chat; June–August were extracted from the uploaded PDFs.

Sheet USER_GUIDE
A1: USER GUIDE
A2: A simple guide to understanding and using this Mercado Pago workbook — no technical knowledge required
A4: START HERE — UNDER 5 MINUTES
A5: 1 | B5: Open Executive Summary for the headline totals, main topics, highlights, and recommended actions.
A6: 2 | B6: Open Trends & Insights to see monthly cash flow, low-balance risk, and the largest outflow categories.
A7: 3 | B7: Use Transactions only when you need to check a specific payment, date, category, counterparty, or balance.
A8: 4 | B8: Check Reconciliation before relying on the analysis: PASS means the monthly transaction totals agree with the statement.
A10: WHAT EACH SHEET IS FOR
A11: Sheet | B11: What you will find | E11: Use it when you want to…
A12: Read Me | B12: Scope, definitions, and source-handling rules. | E12: Understand how the workbook was prepared.
A13: Executive Summary | B13: A five-minute overview with totals, highlights, and actions. | E13: Get the answer quickly.
A14: Trends & Insights | B14: Charts, key indicators, monthly trends, and interpretation. | E14: See patterns and financial risks.
A15: Dashboard | B15: Headline indicators and a compact monthly snapshot. | E15: Monitor the account at a glance.
A16: Monthly Summary | B16: Opening, inflows, outflows, closing, net movement, and variances by month. | E16: Compare one month with another.
A17: Transactions | B17: All 326 unique operations with dates, descriptions, categories, and balances. | E17: Investigate a particular transaction.
A18: Outflow Categories | B18: Spending totals and shares by analytical category. | E18: Understand where money went.
A19: Counterparties | B19: Names grouped by transaction count and money moved. | E19: Find recurring or concentrated relationships.
A20: Reconciliation | B20: Checks against statement totals and the source register. | E20: Confirm completeness and duplicate handling.
A21: Analysis & Chat | B21: Detailed month-by-month analytical notes. | E21: Read the reasoning behind the conclusions.
A23: SIMPLE MONTHLY ROUTINE
A24: Step | B24: What to do | F24: Where to check
A25: 1 | B25: Confirm the new month appears and the transaction count looks reasonable. | F25: Dashboard / Monthly Summary
A26: 2 | B26: Confirm Reconciliation says PASS and all variances are zero. | F26: Reconciliation
A27: 3 | B27: Review the monthly net movement and minimum observed balance. | F27: Trends & Insights
A28: 4 | B28: Investigate unusually large payments or unfamiliar counterparties. | F28: Transactions / Counterparties
A29: 5 | B29: Update your cash-buffer and payment-timing actions if liquidity was tight. | F29: Executive Summary
A31: SAFE USE — WHAT YOU MAY AND MAY NOT CHANGE
A32: • Use filters and sorting in the data tables to find information; this does not change the underlying transactions.
A33: • You may add notes in a new blank column, but avoid overwriting existing formulas, table headers, operation IDs, or balances.
A34: • Do not delete rows that look duplicated unless the operation ID and source control have been checked first.
A35: • Treat transfers and credit-card settlements separately from ordinary consumption; combining them can distort spending.
A36: • If a reconciliation status stops showing PASS, pause and review the source and formulas before using the totals.
A38: PLAIN-LANGUAGE GLOSSARY
A39: Inflows | B39: Money entering the Mercado Pago account.
A40: Outflows | B40: Money leaving the account.
A41: Net movement | B41: Inflows minus outflows. Positive means cash increased; negative means cash decreased.
A42: Closing balance | B42: The account balance at the end of the month.
A43: Minimum balance | B43: The lowest balance observed after any transaction during the month.
A44: Reconciliation | B44: A check that calculated transaction totals match the statement totals.
A47: IMPORTANT LIMITATIONS
A48: • Categories are analytical labels based on transaction descriptions; they are not formal accounting or tax classifications.
A49: • Credit-card settlements show when the card bill was paid, not necessarily when the underlying purchases occurred.
A50: • April and May were transcribed from statement text; June through August were extracted from PDFs.
A51: • MercadoPago 4.pdf duplicates June and is deliberately excluded, so it does not inflate the 326-transaction total.

Sheet Executive Summary
A1: Mercado Pago — Executive Summary
A2: Five-minute guide to activity from April–August 2026 | 326 unique transactions
A4: Total Transactions | C4: Total Inflows | E4: Total Outflows | G4: Net Cash Movement
A5: =COUNTA(Transactions!D5:D330) -> 326 | C5: =SUMIFS(Transactions!E5:E330,Transactions!F5:F330,"Inflow") -> 105270.27 | E5: =-SUMIFS(Transactions!E5:E330,Transactions!F5:F330,"Outflow") -> 114588.63 | G5: =SUM(Transactions!E5:E330) -> -9318.36
A8: MAIN TOPICS
A9: Topic | B9: What it means / where to look
A10: Cash position | B10: Monthly openings, inflows, outflows, closing balances and net movement — Monthly Summary and Dashboard.
A11: Transaction detail | B11: 326 unique operations with date, category, counterparty and running balance — Transactions.
A12: Spending structure | B12: Outflows split between transfers, card settlements and ordinary consumption — Outflow Categories.
A13: Counterparties | B13: Recurring names and absolute flow concentration — Counterparties.
A14: Controls | B14: All five months reconcile; duplicate June source is excluded — Reconciliation.
A16: TOP HIGHLIGHTS
A17: • Net cash movement was −R$9,318.36: inflows of R$105,270.27 did not cover R$114,588.63 of outflows.
A18: • July was the weakest month (−R$19,796.12); June was strongest (+R$10,042.74). Only 2 of 5 months were negative.
A19: • Liquidity was tight every month: the observed minimum stayed below R$500, reaching R$0.00 in August.
A20: • Transfers plus credit-card settlements represented 67.1% of all outflows, so they should be separated from ordinary consumption.
A21: • All five monthly statements passed reconciliation; the duplicate June source does not inflate the 326-transaction total.
A24: ACTION ITEMS
A25: Priority | B25: Action | C25: Why it matters
A26: High | B26: Set a minimum operating cash buffer and alert threshold. | C26: All five months fell below R$500; four approached R$33 or less.
A27: High | B27: Schedule large card and bill payments against confirmed funding dates. | C27: The largest outflow was R$9,377.49; card settlements reached R$29,540.63.
A28: Medium | B28: Budget ordinary consumption separately from transfers and card settlements. | C28: Those two categories make up 67.1% of outflows and can distort spending analysis.
A29: Medium | B29: Review recurring personal transfers and standardize counterparty names. | C29: Name variants fragment the counterparty view and make recurring flows harder to monitor.
A30: Routine | B30: Continue monthly reconciliation and duplicate-source control. | C30: Current controls passed for every included month and should remain in place.

Sheet Trends & Insights
A1: Trends & Insights
A2: Cash flow, liquidity pressure and outflow concentration | April–August 2026
A4: STORY IN BRIEF
A5: The account ended the five-month period R$9,318.36 lower despite large, concentrated funding transfers.
A6: Monthly performance swung sharply: June added R$10,042.74, while July consumed R$19,796.12.
A7: Liquidity is the clearest risk signal: every month reached below R$500, and four months reached about R$33 or less.
A8: Transfers and card settlements dominate outflows, while ordinary spending is led by bills, groceries and e-commerce.
A10: Months Below R$500 | D10: Negative Months | G10: Transfer + Card Share | I10: Funding Concentration
A11: =COUNTIF(F15:F19,"<500") -> 5 | D11: =COUNTIF(D15:D19,"<0") -> 2 | G11: =SUM('Outflow Categories'!B5:B6)/SUM('Outflow Categories'!B5:B24) -> 0.67096072 | I11: =(SUMIFS(Transactions!E5:E330,Transactions!I5:I330,"EDUARDO F GIOVANNINI",Transactions!F5:F330,"Inflow")+SUMIFS(Transactions!E5:E330,Transactions!I5:I330,"EDUARDO FORSTER GIOVANNINI",Transactions!F5:F330,"Inflow"))/SUMIFS(Transactions!E5:E330,Transactions!F5:F330,"Inflow") -> 0.96228679
A14: Month | B14: Inflows | C14: Outflows | D14: Net | E14: Closing | F14: Minimum Balance
A15: ='Monthly Summary'!B5 -> April 2026 | B15: ='Monthly Summary'!H5 -> 27262.06 | C15: ='Monthly Summary'!I5 -> 21193.04 | D15: ='Monthly Summary'!J5 -> 6069.02 | E15: ='Monthly Summary'!F5 -> 27224.11 | F15: =Dashboard!H11 -> 30.9
A16: ='Monthly Summary'!B6 -> May 2026 | B16: ='Monthly Summary'!H6 -> 17065.63 | C16: ='Monthly Summary'!I6 -> 30217.29 | D16: ='Monthly Summary'!J6 -> -13151.66 | E16: ='Monthly Summary'!F6 -> 14072.45 | F16: =Dashboard!H12 -> 471.2
A17: ='Monthly Summary'!B7 -> June 2026 | B17: ='Monthly Summary'!H7 -> 24151.04 | C17: ='Monthly Summary'!I7 -> 14108.3 | D17: ='Monthly Summary'!J7 -> 10042.74 | E17: ='Monthly Summary'!F7 -> 24115.19 | F17: =Dashboard!H13 -> 0.88
A18: ='Monthly Summary'!B8 -> July 2026 | B18: ='Monthly Summary'!H8 -> 11272.89 | C18: ='Monthly Summary'!I8 -> 31069.01 | D18: ='Monthly Summary'!J8 -> -19796.12 | E18: ='Monthly Summary'!F8 -> 4319.07 | F18: =Dashboard!H14 -> 33.11
A19: ='Monthly Summary'!B9 -> August 2026 | B19: ='Monthly Summary'!H9 -> 25518.65 | C19: ='Monthly Summary'!I9 -> 18000.99 | D19: ='Monthly Summary'!J9 -> 7517.66 | E19: ='Monthly Summary'!F9 -> 11836.73 | F19: =Dashboard!H15 -> 0
A40: Outflow Category | B40: Amount | C40: Share
A41: ='Outflow Categories'!A5 -> Person / External Transfer | B41: ='Outflow Categories'!B5 -> 47343.84 | C41: ='Outflow Categories'!C5 -> 0.4131635
A42: ='Outflow Categories'!A6 -> Credit Card Settlement | B42: ='Outflow Categories'!B6 -> 29540.63 | C42: ='Outflow Categories'!C6 -> 0.25779722
A43: ='Outflow Categories'!A7 -> Bills & Services | B43: ='Outflow Categories'!B7 -> 9790.6 | C43: ='Outflow Categories'!C7 -> 0.085441287
A44: ='Outflow Categories'!A8 -> Groceries & Food | B44: ='Outflow Categories'!B8 -> 6716.58 | C44: ='Outflow Categories'!C8 -> 0.058614716
A45: ='Outflow Categories'!A9 -> E-commerce | B45: ='Outflow Categories'!B9 -> 4805.39 | C45: ='Outflow Categories'!C9 -> 0.041936011
A46: ='Outflow Categories'!A10 -> Travel | B46: ='Outflow Categories'!B10 -> 3529.31 | C46: ='Outflow Categories'!C10 -> 0.030799827
A56: KEY INSIGHTS
A57: 1. Cash-flow volatility is high: the gap between the best and worst monthly net movement is R$29,838.86.
A58: 2. Account-holder funding names supplied about 96.2% of inflows, indicating strong dependence on concentrated transfers.
A59: 3. Person/external transfers are the largest outflow category (R$47,343.84; 41.3%), followed by card settlements (R$29,540.63; 25.8%).
A60: 4. Among ordinary categories, bills & services (R$9,790.60) and groceries & food (R$6,716.58) are the largest.
A61: 5. Reconciliation quality is strong: all included months pass, and the duplicated June source is explicitly excluded.

Sheet Dashboard
A1: Mercado Pago — April to August 2026
A2: Professional transaction workbook | 5 unique months | June duplicate source excluded from transaction totals
A4: Total Transactions | C4: Total Inflows | E4: Total Outflows | G4: Net Cash Movement | I4: Investment Yield | K4: Min. Observed Balance
A5: 326 | C5: 105270.27 | E5: 114588.63 | G5: -9318.36 | I5: 251.08 | K5: 0
A9: Monthly Snapshot
A10: Month | B10: Transactions | C10: Opening | D10: Inflows | E10: Outflows | F10: Net | G10: Closing | H10: Minimum Balance | I10: Reconciliation
A11: 2026-04 | B11: 64 | C11: 21155.09 | D11: 27262.06 | E11: 21193.04 | F11: 6069.02 | G11: 27224.11 | H11: 30.9 | I11: PASS
A12: 2026-05 | B12: 76 | C12: 27224.11 | D12: 17065.63 | E12: 30217.29 | F12: -13151.66 | G12: 14072.45 | H12: 471.2 | I12: PASS
A13: 2026-06 | B13: 47 | C13: 14072.45 | D13: 24151.04 | E13: 14108.3 | F13: 10042.74 | G13: 24115.19 | H13: 0.88 | I13: PASS
A14: 2026-07 | B14: 69 | C14: 24115.19 | D14: 11272.89 | E14: 31069.01 | F14: -19796.12 | G14: 4319.07 | H14: 33.11 | I14: PASS
A15: 2026-08 | B15: 70 | C15: 4319.07 | D15: 25518.65 | E15: 18000.99 | F15: 7517.66 | G15: 11836.73 | H15: 0 | I15: PASS

Sheet Monthly Summary
A1: Monthly Summary
A2: Statement-level reported totals vs. transaction-level calculated totals
A4: Month | B4: Period | C4: Opening | D4: Reported Inflows | E4: Reported Outflows | F4: Closing | G4: Reconciliation | H4: Calculated Inflows | I4: Calculated Outflows | J4: Calculated Net | K4: Reported Net | L4: Variance Inflows | M4: Variance Outflows | N4: Variance Closing
A5: 2026-04 | B5: April 2026 | C5: 21155.09 | D5: 27262.06 | E5: 21193.04 | F5: 27224.11 | G5: PASS | H5: 27262.06 | I5: 21193.04 | J5: 6069.02 | K5: 6069.02 | L5: -3.6379788e-12 | M5: 0 | N5: -3.6379788e-12
A6: 2026-05 | B6: May 2026 | C6: 27224.11 | D6: 17065.63 | E6: 30217.29 | F6: 14072.45 | G6: PASS | H6: 17065.63 | I6: 30217.29 | J6: -13151.66 | K6: -13151.66 | L6: -3.6379788e-12 | M6: 0 | N6: -3.6379788e-12
A7: 2026-06 | B7: June 2026 | C7: 14072.45 | D7: 24151.04 | E7: 14108.3 | F7: 24115.19 | G7: PASS | H7: 24151.04 | I7: 14108.3 | J7: 10042.74 | K7: 10042.74 | L7: -3.6379788e-12 | M7: 0 | N7: 0
A8: 2026-07 | B8: July 2026 | C8: 24115.19 | D8: 11272.89 | E8: 31069.01 | F8: 4319.07 | G8: PASS | H8: 11272.89 | I8: 31069.01 | J8: -19796.12 | K8: -19796.12 | L8: 0 | M8: 3.6379788e-12 | N8: -3.6379788e-12
A9: 2026-08 | B9: August 2026 | C9: 4319.07 | D9: 25518.65 | E9: 18000.99 | F9: 11836.73 | G9: PASS | H9: 25518.65 | I9: 18000.99 | J9: 7517.66 | K9: 7517.66 | L9: 0 | M9: -3.6379788e-12 | N9: 3.6379788e-12

Sheet Transactions
A1: Transactions
A2: 326 unique transactions | June duplicate source excluded from transaction rows
A4: Month | B4: Date | C4: Description | D4: Operation ID | E4: Amount | F4: Direction | G4: Category | H4: Subcategory | I4: Counterparty | J4: Balance | K4: Source | L4: Amount Absolute | M4: Transaction Key | N4: Source Status
A5: 2026-04 | B5: 46113 | C5: Pix enviado Eva Bezerra da Silva Brandao | D5: 152151991553 | E5: -2080 | F5: Outflow | G5: Person / External Transfer | H5: Sent Pix | I5: Eva Bezerra da Silva Brandao | J5: 18916.94 | K5: User-supplied statement text | L5: 2080 | M5: 2026-04-152151991553 | N5: Unique transaction
A6: 2026-04 | B6: 46113 | C6: Pix enviado Marinaldo Domingos de Souza | D6: 152189207147 | E6: -700 | F6: Outflow | G6: Person / External Transfer | H6: Sent Pix | I6: Marinaldo Domingos de Souza | J6: 18216.94 | K6: User-supplied statement text | L6: 700 | M6: 2026-04-152189207147 | N6: Unique transaction
A7: 2026-04 | B7: 46113 | C7: Pagamento com QR Pix ESTACAO 89 COMERCIO VAREJISTA DE ALIMENTOS LTDA | D7: 152833636626 | E7: -113.8 | F7: Outflow | G7: Groceries & Food | H7: Groceries / food | I7: ESTACAO 89 COMERCIO VAREJISTA DE ALIMENTOS LTDA | J7: 21050.87 | K7: User-supplied statement text | L7: 113.8 | M7: 2026-04-152833636626 | N7: Unique transaction
A8: 2026-04 | B8: 46113 | C8: Pagamento com QR Pix EDGLEY DE SOUSA FORMIGA | D8: 152834775544 | E8: -53.93 | F8: Outflow | G8: Person / External Transfer | H8: Sent Pix | I8: EDGLEY DE SOUSA FORMIGA | J8: 20996.94 | K8: User-supplied statement text | L8: 53.93 | M8: 2026-04-152834775544 | N8: Unique transaction
A9: 2026-04 | B9: 46113 | C9: Rendimentos | D9: 1741805550939 | E9: 9.58 | F9: Inflow | G9: Investment Yield | H9: Rendimentos | I9: Mercado Pago / Investment | J9: 21164.67 | K9: User-supplied statement text | L9: 9.58 | M9: 2026-04-1741805550939 | N9: Unique transaction
A10: 2026-04 | B10: 46114 | C10: Pagamento com QR Pix IATA INTERNATIONAL AIR TRANSPORT ASSOCIATION | D10: 152210734999 | E10: -1422.71 | F10: Outflow | G10: Travel | H10: Travel | I10: IATA INTERNATIONAL AIR TRANSPORT ASSOCIATION | J10: 16802.56 | K10: User-supplied statement text | L10: 1422.71 | M10: 2026-04-152210734999 | N10: Unique transaction
A11: 2026-04 | B11: 46114 | C11: Pagamento com QR Pix COMPANHIA DE AGUA E ESGOTOS DA PARAIBA CAGEPA | D11: 152211492245 | E11: -227.03 | F11: Outflow | G11: Utilities | H11: Electricity / water | I11: COMPANHIA DE AGUA E ESGOTOS DA PARAIBA CAGEPA | J11: 16575.53 | K11: User-supplied statement text | L11: 227.03 | M11: 2026-04-152211492245 | N11: Unique transaction
A12: 2026-04 | B12: 46114 | C12: Pix enviado Eduardo Silva dos Santos | D12: 152285797203 | E12: -350 | F12: Outflow | G12: Person / External Transfer | H12: Sent Pix | I12: Eduardo Silva dos Santos | J12: 16113.26 | K12: User-supplied statement text | L12: 350 | M12: 2026-04-152285797203 | N12: Unique transaction
A13: 2026-04 | B13: 46114 | C13: Pagamento com QR Pix REDE MENOR PRECO SUPERMERCADO LTDA | D13: 152309349407 | E13: -253.88 | F13: Outflow | G13: Groceries & Food | H13: Groceries / food | I13: REDE MENOR PRECO SUPERMERCADO LTDA | J13: 15791.59 | K13: User-supplied statement text | L13: 253.88 | M13: 2026-04-152309349407 | N13: Unique transaction
A14: 2026-04 | B14: 46114 | C14: Pix enviado Estacao 89 Comercio Varejista de Alimentos Ltda | D14: 152317783031 | E14: -75.5 | F14: Outflow | G14: Groceries & Food | H14: Groceries / food | I14: Estacao 89 Comercio Varejista de Alimentos Ltda | J14: 15716.09 | K14: User-supplied statement text | L14: 75.5 | M14: 2026-04-152317783031 | N14: Unique transaction
A15: 2026-04 | B15: 46114 | C15: Pagamento com QR Pix REDE BOM COMERCIO LTDA | D15: 152995794336 | E15: -112.27 | F15: Outflow | G15: Person / External Transfer | H15: Sent Pix | I15: REDE BOM COMERCIO LTDA | J15: 16463.26 | K15: User-supplied statement text | L15: 112.27 | M15: 2026-04-152995794336 | N15: Unique transaction
A16: 2026-04 | B16: 46114 | C16: Pagamento de conta Vivo Móvel SP | D16: 153040899150 | E16: -67.79 | F16: Outflow | G16: Telecommunications | H16: Mobile / telecom | I16: Vivo Móvel SP | J16: 16045.47 | K16: User-supplied statement text | L16: 67.79 | M16: 2026-04-153040899150 | N16: Unique transaction
... A73: 2026-05 | B73: 46146 | C73: Rendimentos | D73: 1743176355208 | E73: 11.65 | F73: Inflow | G73: Investment Yield | H73: Rendimentos | I73: Mercado Pago / Investment | J73: 23975.76 | K73: User-supplied statement text | L73: 11.65 | M73: 2026-05-1743176355208 | N73: Unique transaction
A74: 2026-05 | B74: 46147 | C74: Pagamento Cartão de crédito | D74: 157139914617 | E74: -8627.35 | F74: Outflow | G74: Credit Card Settlement | H74: Credit card | J74: 12875.06 | K74: User-supplied statement text | L74: 8627.35 | M74: 2026-05-157139914617 | N74: Unique transaction
A75: 2026-05 | B75: 46147 | C75: Pagamento SALUTARE MEDICINA E SAUDE | D75: 157802402212 | E75: -130.91 | F75: Outflow | G75: Health | H75: Health / pharmacy | I75: Pagamento SALUTARE MEDICINA E SAUDE | J75: 23675.09 | K75: User-supplied statement text | L75: 130.91 | M75: 2026-05-157802402212 | N75: Unique transaction
A76: 2026-05 | B76: 46147 | C76: Pix enviado Eduardo Silva dos Santos | D76: 157905028464 | E76: -450 | F76: Outflow | G76: Person / External Transfer | H76: Sent Pix | I76: Eduardo Silva dos Santos | J76: 23225.09 | K76: User-supplied statement text | L76: 450 | M76: 2026-05-157905028464 | N76: Unique transaction
A77: 2026-05 | B77: 46147 | C77: Pagamento Cartão de crédito | D77: 157907424040 | E77: -1722.68 | F77: Outflow | G77: Credit Card Settlement | H77: Credit card | J77: 21502.41 | K77: User-supplied statement text | L77: 1722.68 | M77: 2026-05-157907424040 | N77: Unique transaction
A78: 2026-05 | B78: 46147 | C78: Rendimentos | D78: 1743260411771 | E78: 10.24 | F78: Inflow | G78: Investment Yield | H78: Rendimentos | I78: Mercado Pago / Investment | J78: 23806 | K78: User-supplied statement text | L78: 10.24 | M78: 2026-05-1743260411771 | N78: Unique transaction
A79: 2026-05 | B79: 46148 | C79: Pagamento com QR Pix EDGLEY DE SOUSA FORMIGA | D79: 157214670055 | E79: -198.35 | F79: Outflow | G79: Person / External Transfer | H79: Sent Pix | I79: EDGLEY DE SOUSA FORMIGA | J79: 12454.45 | K79: User-supplied statement text | L79: 198.35 | M79: 2026-05-157214670055 | N79: Unique transaction
A80: 2026-05 | B80: 46148 | C80: Pix enviado Gleudson Silva Farias | D80: 157231141069 | E80: -1260 | F80: Outflow | G80: Person / External Transfer | H80: Sent Pix | I80: Gleudson Silva Farias | J80: 11194.45 | K80: User-supplied statement text | L80: 1260 | M80: 2026-05-157231141069 | N80: Unique transaction
A81: 2026-05 | B81: 46148 | C81: Pix enviado Casa dos Criadores Comercio Ltda | D81: 157252225025 | E81: -281 | F81: Outflow | G81: Purchases & Services | H81: Business / service | I81: Casa dos Criadores Comercio Ltda | J81: 10913.45 | K81: User-supplied statement text | L81: 281 | M81: 2026-05-157252225025 | N81: Unique transaction
A82: 2026-05 | B82: 46148 | C82: Pagamento com QR Pix MERCADINHO LACANTO LTDA | D82: 157981953362 | E82: -232.44 | F82: Outflow | G82: Groceries & Food | H82: Groceries / food | I82: MERCADINHO LACANTO LTDA | J82: 12652.8 | K82: User-supplied statement text | L82: 232.44 | M82: 2026-05-157981953362 | N82: Unique transaction
A83: 2026-05 | B83: 46148 | C83: Pix enviado Casa dos Criadores Comercio Ltda | D83: 158021830828 | E83: -15 | F83: Outflow | G83: Purchases & Services | H83: Business / service | I83: Casa dos Criadores Comercio Ltda | J83: 10898.45 | K83: User-supplied statement text | L83: 15 | M83: 2026-05-158021830828 | N83: Unique transaction
A84: 2026-05 | B84: 46148 | C84: Rendimentos | D84: 1743324850487 | E84: 10.18 | F84: Inflow | G84: Investment Yield | H84: Rendimentos | I84: Mercado Pago / Investment | J84: 12885.24 | K84: User-supplied statement text | L84: 10.18 | M84: 2026-05-1743324850487 | N84: Unique transaction
A85: 2026-05 | B85: 46149 | C85: Pagamento com QR Pix VINDI PAGAMENTOS SA | D85: 157467292465 | E85: -494.8 | F85: Outflow | G85: Purchases & Services | H85: Business / service | I85: VINDI PAGAMENTOS SA | J85: 10408.38 | K85: User-supplied statement text | L85: 494.8 | M85: 2026-05-157467292465 | N85: Unique transaction
A86: 2026-05 | B86: 46149 | C86: Rendimentos | D86: 1743387752167 | E86: 4.73 | F86: Inflow | G86: Investment Yield | H86: Rendimentos | I86: Mercado Pago / Investment | J86: 10903.18 | K86: User-supplied statement text | L86: 4.73 | M86: 2026-05-1743387752167 | N86: Unique transaction
A87: 2026-05 | B87: 46150 | C87: Pagamento com QR Pix PANIFICADORA SAO GONCALO LTDA | D87: 157566215629 | E87: -78.91 | F87: Outflow | G87: Groceries & Food | H87: Groceries / food | I87: PANIFICADORA SAO GONCALO LTDA | J87: 10082.76 | K87: User-supplied statement text | L87: 78.91 | M87: 2026-05-157566215629 | N87: Unique transaction
A88: 2026-05 | B88: 46150 | C88: Pagamento com QR Pix SUPERMERCADO LITORAL LTDA | D88: 157570731541 | E88: -430.42 | F88: Outflow | G88: Groceries & Food | H88: Groceries / food | I88: SUPERMERCADO LITORAL LTDA | J88: 9652.34 | K88: User-supplied statement text | L88: 430.42 | M88: 2026-05-157570731541 | N88: Unique transaction
A89: 2026-05 | B89: 46150 | C89: Pix enviado Eva Bezerra da Silva Brandao | D89: 157589983803 | E89: -1040 | F89: Outflow | G89: Person / External Transfer | H89: Sent Pix | I89: Eva Bezerra da Silva Brandao | J89: 8612.34 | K89: User-supplied statement text | L89: 1040 | M89: 2026-05-157589983803 | N89: Unique transaction
A90: 2026-05 | B90: 46150 | C90: Pagamento Mercado Libre | D90: 157607162465 | E90: -390.69 | F90: Outflow | G90: E-commerce | H90: Mercado Libre | J90: 8221.65 | K90: User-supplied statement text | L90: 390.69 | M90: 2026-05-157607162465 | N90: Unique transaction
A91: 2026-05 | B91: 46150 | C91: Pagamento de conta Vivo Móvel SP | D91: 158276307540 | E91: -251.43 | F91: Outflow | G91: Telecommunications | H91: Mobile / telecom | I91: Vivo Móvel SP | J91: 10161.67 | K91: User-supplied statement text | L91: 251.43 | M91: 2026-05-158276307540 | N91: Unique transaction
A92: 2026-05 | B92: 46150 | C92: Rendimentos | D92: 1743455883028 | E92: 4.72 | F92: Inflow | G92: Investment Yield | H92: Rendimentos | I92: Mercado Pago / Investment | J92: 10413.1 | K92: User-supplied statement text | L92: 4.72 | M92: 2026-05-1743455883028 | N92: Unique transaction
A93: 2026-05 | B93: 46151 | C93: Pagamento Mercado Libre | D93: 157692336095 | E93: -379.98 | F93: Outflow | G93: E-commerce | H93: Mercado Libre | J93: 7841.67 | K93: User-supplied statement text | L93: 379.98 | M93: 2026-05-157692336095 | N93: Unique transaction
A94: 2026-05 | B94: 46151 | C94: Pix enviado Eduardo Silva dos Santos | D94: 157713825511 | E94: -350 | F94: Outflow | G94: Person / External Transfer | H94: Sent Pix | I94: Eduardo Silva dos Santos | J94: 7491.67 | K94: User-supplied statement text | L94: 350 | M94: 2026-05-157713825511 | N94: Unique transaction
A95: 2026-05 | B95: 46152 | C95: Pix enviado Estacao 89 Comercio Varejista de Alimentos Ltda | D95: 158711310526 | E95: -97.1 | F95: Outflow | G95: Groceries & Food | H95: Groceries / food | I95: Estacao 89 Comercio Varejista de Alimentos Ltda | J95: 7394.57 | K95: User-supplied statement text | L95: 97.1 | M95: 2026-05-158711310526 | N95: Unique transaction
A96: 2026-05 | B96: 46153 | C96: Pix enviado MEGA BYTE COMPUTADORES | D96: 158738697878 | E96: -386.91 | F96: Outflow | G96: Purchases & Services | H96: Business / service | I96: MEGA BYTE COMPUTADORES | J96: 7011.22 | K96: User-supplied statement text | L96: 386.91 | M96: 2026-05-158738697878 | N96: Unique transaction
A97: 2026-05 | B97: 46153 | C97: Pagamento com QR Pix SECRETARIA DE ESTADO DA FAZENDA SEFAZ PB | D97: 158765690240 | E97: -1342.74 | F97: Outflow | G97: Taxes & Government | H97: Government | I97: SECRETARIA DE ESTADO DA FAZENDA SEFAZ PB | J97: 5668.48 | K97: User-supplied statement text | L97: 1342.74 | M97: 2026-05-158765690240 | N97: Unique transaction
A98: 2026-05 | B98: 46153 | C98: Rendimentos | D98: 1743527514456 | E98: 3.56 | F98: Inflow | G98: Investment Yield | H98: Rendimentos | I98: Mercado Pago / Investment | J98: 7398.13 | K98: User-supplied statement text | L98: 3.56 | M98: 2026-05-1743527514456 | N98: Unique transaction
A99: 2026-05 | B99: 46154 | C99: Pix enviado Eduardo Silva dos Santos | D99: 158199268649 | E99: -350 | F99: Outflow | G99: Person / External Transfer | H99: Sent Pix | I99: Eduardo Silva dos Santos | J99: 5320.94 | K99: User-supplied statement text | L99: 350 | M99: 2026-05-158199268649 | N99: Unique transaction
A100: 2026-05 | B100: 46154 | C100: Pix enviado Maria da Luz Assis da Silva | D100: 158978731712 | E100: -200 | F100: Outflow | G100: Person / External Transfer | H100: Sent Pix | I100: Maria da Luz Assis da Silva | J100: 5120.94 | K100: User-supplied statement text | L100: 200 | M100: 2026-05-158978731712 | N100: Unique transaction
A101: 2026-05 | B101: 46154 | C101: Pagamento com QR Pix ATLANTICO SUL HOTELARIA E RESTAURANTES L | D101: 158997083882 | E101: -110 | F101: Outflow | G101: Dining | H101: Restaurants / delivery | I101: ATLANTICO SUL HOTELARIA E RESTAURANTES L | J101: 5010.94 | K101: User-supplied statement text | L101: 110 | M101: 2026-05-158997083882 | N101: Unique transaction
A102: 2026-05 | B102: 46154 | C102: Pagamento com QR Pix LINDEMBERG FRANCISCO DA SILVA | D102: 159034648594 | E102: -22.85 | F102: Outflow | G102: Person / External Transfer | H102: Sent Pix | I102: LINDEMBERG FRANCISCO DA SILVA | J102: 4988.09 | K102: User-supplied statement text | L102: 22.85 | M102: 2026-05-159034648594 | N102: Unique transaction
A103: 2026-05 | B103: 46154 | C103: Rendimentos | D103: 1743608351070 | E103: 2.46 | F103: Inflow | G103: Investment Yield | H103: Rendimentos | I103: Mercado Pago / Investment | J103: 5670.94 | K103: User-supplied statement text | L103: 2.46 | M103: 2026-05-1743608351070 | N103: Unique transaction
A104: 2026-05 | B104: 46155 | C104: Rendimentos | D104: 1743680014253 | E104: 2.17 | F104: Inflow | G104: Investment Yield | H104: Rendimentos | I104: Mercado Pago / Investment | J104: 4990.26 | K104: User-supplied statement text | L104: 2.17 | M104: 2026-05-1743680014253 | N104: Unique transaction
A105: 2026-05 | B105: 46156 | C105: Pix enviado Gleudson Silva Farias | D105: 158525703339 | E105: -1080 | F105: Outflow | G105: Person / External Transfer | H105: Sent Pix | I105: Gleudson Silva Farias | J105: 3912.43 | K105: User-supplied statement text | L105: 1080 | M105: 2026-05-158525703339 | N105: Unique transaction
... A141: 2026-05 | B141: 46173 | C141: Pix enviado Eva Bezerra da Silva Brandao | D141: 161051451749 | E141: -1110 | F141: Outflow | G141: Person / External Transfer | H141: Sent Pix | I141: Eva Bezerra da Silva Brandao | J141: 15025.48 | K141: User-supplied statement text | L141: 1110 | M141: 2026-05-161051451749 | N141: Unique transaction
A142: 2026-05 | B142: 46173 | C142: Pagamento Mercado Livre | D142: 161087686309 | E142: -249.99 | F142: Outflow | G142: E-commerce | H142: Mercado Libre | J142: 14775.49 | K142: User-supplied statement text | L142: 249.99 | M142: 2026-05-161087686309 | N142: Unique transaction
A143: 2026-05 | B143: 46173 | C143: Pagamento Mercado Libre | D143: 161880342250 | E143: -547.64 | F143: Outflow | G143: E-commerce | H143: Mercado Libre | J143: 14227.85 | K143: User-supplied statement text | L143: 547.64 | M143: 2026-05-161880342250 | N143: Unique transaction
A144: 2026-05 | B144: 46173 | C144: Pagamento com QR Pix ESTACAO 89 COMERCIO VAREJISTA DE ALIMENTOS LTDA | D144: 161901119204 | E144: -155.4 | F144: Outflow | G144: Groceries & Food | H144: Groceries / food | I144: ESTACAO 89 COMERCIO VAREJISTA DE ALIMENTOS LTDA | J144: 14072.45 | K144: User-supplied statement text | L144: 155.4 | M144: 2026-05-161901119204 | N144: Unique transaction
A145: 2026-06 | B145: 46174 | C145: Pagamento com QR Pix EDGLEY DE SOUSA FORMIGA | D145: 161177447109 | E145: -48.72 | F145: Outflow | G145: Person / External Transfer | H145: Sent Pix | I145: EDGLEY DE SOUSA FORMIGA | J145: 14031.16 | K145: MercadoPago.pdf | L145: 48.72 | M145: 2026-06-161177447109 | N145: Unique transaction
A146: 2026-06 | B146: 46174 | C146: Pagamento com QR Pix MERCADINHO LACANTO LTDA | D146: 161972213288 | E146: -165.9 | F146: Outflow | G146: Groceries & Food | H146: Groceries / food | I146: MERCADINHO LACANTO LTDA | J146: 13865.26 | K146: MercadoPago.pdf | L146: 165.9 | M146: 2026-06-161972213288 | N146: Unique transaction
A147: 2026-06 | B147: 46174 | C147: Pagamento com QR Pix EDGLEY DE SOUSA FORMIGA | D147: 161993896860 | E147: -55.71 | F147: Outflow | G147: Person / External Transfer | H147: Sent Pix | I147: EDGLEY DE SOUSA FORMIGA | J147: 13809.55 | K147: MercadoPago.pdf | L147: 55.71 | M147: 2026-06-161993896860 | N147: Unique transaction
A148: 2026-06 | B148: 46174 | C148: Rendimentos | D148: 1744539734583 | E148: 7.43 | F148: Inflow | G148: Investment Yield | H148: Rendimentos | I148: Mercado Pago / Investment | J148: 14079.88 | K148: MercadoPago.pdf | L148: 7.43 | M148: 2026-06-1744539734583 | N148: Unique transaction
A149: 2026-06 | B149: 46175 | C149: Pix enviado Estacao 89 Comercio Varejista de Alimentos Ltda | D149: 161457148295 | E149: -119.4 | F149: Outflow | G149: Groceries & Food | H149: Groceries / food | I149: Estacao 89 Comercio Varejista de Alimentos Ltda | J149: 12596.13 | K149: MercadoPago.pdf | L149: 119.4 | M149: 2026-06-161457148295 | N149: Unique transaction
A150: 2026-06 | B150: 46175 | C150: Pix enviado Jonathan Borba da Silva | D150: 162229671794 | E150: -100 | F150: Outflow | G150: Person / External Transfer | H150: Sent Pix | I150: Jonathan Borba da Silva | J150: 12715.53 | K150: MercadoPago.pdf | L150: 100 | M150: 2026-06-162229671794 | N150: Unique transaction
A151: 2026-06 | B151: 46175 | C151: Pix enviado Ewerton de Sousa Emeri | D151: 162231392520 | E151: -1000 | F151: Outflow | G151: Person / External Transfer | H151: Sent Pix | I151: Ewerton de Sousa Emeri | J151: 12815.53 | K151: MercadoPago.pdf | L151: 1000 | M151: 2026-06-162231392520 | N151: Unique transaction
A152: 2026-06 | B152: 46175 | C152: Rendimentos | D152: 1744624699005 | E152: 5.98 | F152: Inflow | G152: Investment Yield | H152: Rendimentos | I152: Mercado Pago / Investment | J152: 13815.53 | K152: MercadoPago.pdf | L152: 5.98 | M152: 2026-06-1744624699005 | N152: Unique transaction
A153: 2026-06 | B153: 46176 | C153: Pix enviado Eduardo Silva dos Santos | D153: 161612165053 | E153: -350 | F153: Outflow | G153: Person / External Transfer | H153: Sent Pix | I153: Eduardo Silva dos Santos | J153: 11052.12 | K153: MercadoPago.pdf | L153: 350 | M153: 2026-06-161612165053 | N153: Unique transaction
A154: 2026-06 | B154: 46176 | C154: Pagamento com QR Pix PEDRO HENRIQUE ALMEIDA DANTAS | D154: 162363729096 | E154: -1200 | F154: Outflow | G154: Person / External Transfer | H154: Sent Pix | I154: PEDRO HENRIQUE ALMEIDA DANTAS | J154: 11402.12 | K154: MercadoPago.pdf | L154: 1200 | M154: 2026-06-162363729096 | N154: Unique transaction
A155: 2026-06 | B155: 46176 | C155: Rendimentos | D155: 1744683051011 | E155: 5.99 | F155: Inflow | G155: Investment Yield | H155: Rendimentos | I155: Mercado Pago / Investment | J155: 12602.12 | K155: MercadoPago.pdf | L155: 5.99 | M155: 2026-06-1744683051011 | N155: Unique transaction
... A174: 2026-06 | B174: 46182 | C174: Rendimentos | D174: 1744963697093 | E174: 3.3 | F174: Inflow | G174: Investment Yield | H174: Rendimentos | I174: Mercado Pago / Investment | J174: 7609.85 | K174: MercadoPago.pdf | L174: 3.3 | M174: 2026-06-1744963697093 | N174: Unique transaction
A175: 2026-06 | B175: 46183 | C175: Pagamento Cartão de crédito | D175: 163466907332 | E175: -6813.48 | F175: Outflow | G175: Credit Card Settlement | H175: Credit card | J175: 799.66 | K175: MercadoPago.pdf | L175: 6813.48 | M175: 2026-06-163466907332 | N175: Unique transaction
A176: 2026-06 | B176: 46183 | C176: Rendimentos | D176: 1745028810537 | E176: 3.29 | F176: Inflow | G176: Investment Yield | H176: Rendimentos | I176: Mercado Pago / Investment | J176: 7613.14 | K176: MercadoPago.pdf | L176: 3.29 | M176: 2026-06-1745028810537 | N176: Unique transaction
A177: 2026-06 | B177: 46184 | C177: Rendimentos | D177: 1745099110608 | E177: 0.35 | F177: Inflow | G177: Investment Yield | H177: Rendimentos | I177: Mercado Pago / Investment | J177: 800.01 | K177: MercadoPago.pdf | L177: 0.35 | M177: 2026-06-1745099110608 | N177: Unique transaction
A178: 2026-06 | B178: 46185 | C178: Rendimentos | D178: 1745172275984 | E178: 0.35 | F178: Inflow | G178: Investment Yield | H178: Rendimentos | I178: Mercado Pago / Investment | J178: 800.36 | K178: MercadoPago.pdf | L178: 0.35 | M178: 2026-06-1745172275984 | N178: Unique transaction
A179: 2026-06 | B179: 46186 | C179: Pix enviado Maria da Luz Assis da Silva | D179: 163965988564 | E179: -150 | F179: Outflow | G179: Person / External Transfer | H179: Sent Pix | I179: Maria da Luz Assis da Silva | J179: 650.36 | K179: MercadoPago.pdf | L179: 150 | M179: 2026-06-163965988564 | N179: Unique transaction
A180: 2026-06 | B180: 46187 | C180: Pix enviado Eva Bezerra da Silva Brandao | D180: 164100571848 | E180: -590 | F180: Outflow | G180: Person / External Transfer | H180: Sent Pix | I180: Eva Bezerra da Silva Brandao | J180: 60.36 | K180: MercadoPago.pdf | L180: 590 | M180: 2026-06-164100571848 | N180: Unique transaction
A181: 2026-06 | B181: 46188 | C181: Rendimentos | D181: 1745239670517 | E181: 0.35 | F181: Inflow | G181: Investment Yield | H181: Rendimentos | I181: Mercado Pago / Investment | J181: 60.71 | K181: MercadoPago.pdf | L181: 0.35 | M181: 2026-06-1745239670517 | N181: Unique transaction
A182: 2026-06 | B182: 46189 | C182: Rendimentos | D182: 1745286157555 | E182: 0.03 | F182: Inflow | G182: Investment Yield | H182: Rendimentos | I182: Mercado Pago / Investment | J182: 60.74 | K182: MercadoPago.pdf | L182: 0.03 | M182: 2026-06-1745286157555 | N182: Unique transaction
A183: 2026-06 | B183: 46190 | C183: Rendimentos | D183: 1745360513722 | E183: 0.03 | F183: Inflow | G183: Investment Yield | H183: Rendimentos | I183: Mercado Pago / Investment | J183: 60.77 | K183: MercadoPago.pdf | L183: 0.03 | M183: 2026-06-1745360513722 | N183: Unique transaction
A184: 2026-06 | B184: 46191 | C184: Rendimentos | D184: 1745429382164 | E184: 0.02 | F184: Inflow | G184: Investment Yield | H184: Rendimentos | I184: Mercado Pago / Investment | J184: 60.79 | K184: MercadoPago.pdf | L184: 0.02 | M184: 2026-06-1745429382164 | N184: Unique transaction
A185: 2026-06 | B185: 46192 | C185: Pagamento com QR Pix JACARE COMERCIO DE COMBUSTIVEIS LTDA | D185: 164088596127 | E185: -32.99 | F185: Outflow | G185: Fuel | H185: Fuel station | I185: JACARE COMERCIO DE COMBUSTIVEIS LTDA | J185: 27.83 | K185: MercadoPago.pdf | L185: 32.99 | M185: 2026-06-164088596127 | N185: Unique transaction
A186: 2026-06 | B186: 46192 | C186: Rendimentos | D186: 1745498110981 | E186: 0.03 | F186: Inflow | G186: Investment Yield | H186: Rendimentos | I186: Mercado Pago / Investment | J186: 60.82 | K186: MercadoPago.pdf | L186: 0.03 | M186: 2026-06-1745498110981 | N186: Unique transaction
A187: 2026-06 | B187: 46194 | C187: Pagamento com QR Pix JACARE COMERCIO DE COMBUSTIVEIS LTDA | D187: 164328795951 | E187: -26.95 | F187: Outflow | G187: Fuel | H187: Fuel station | I187: JACARE COMERCIO DE COMBUSTIVEIS LTDA | J187: 0.88 | K187: MercadoPago.pdf | L187: 26.95 | M187: 2026-06-164328795951 | N187: Unique transaction
... A201: 2026-07 | B201: 46208 | C201: Pagamento com QR Pix TELEFONICA BRASIL S.A. | D201: 166510300355 | E201: -74.02 | F201: Outflow | G201: Telecommunications | H201: Mobile / telecom | I201: TELEFONICA BRASIL S.A. | J201: 10102.81 | K201: MercadoPago 3.pdf | L201: 74.02 | M201: 2026-07-166510300355 | N201: Unique transaction
A202: 2026-07 | B202: 46209 | C202: Pagamento Cartão de crédito | D202: 166560927621 | E202: -3803.89 | F202: Outflow | G202: Credit Card Settlement | H202: Credit card | J202: 5970.69 | K202: MercadoPago 3.pdf | L202: 3803.89 | M202: 2026-07-166560927621 | N202: Unique transaction
A203: 2026-07 | B203: 46209 | C203: Pagamento com QR Pix TIM S A | D203: 166564097417 | E203: -288.58 | F203: Outflow | G203: Telecommunications | H203: Mobile / telecom | I203: TIM S A | J203: 9774.58 | K203: MercadoPago 3.pdf | L203: 288.58 | M203: 2026-07-166564097417 | N203: Unique transaction
A204: 2026-07 | B204: 46209 | C204: Pagamento com QR Pix TIM S A | D204: 166564228585 | E204: -47.99 | F204: Outflow | G204: Telecommunications | H204: Mobile / telecom | I204: TIM S A | J204: 10063.16 | K204: MercadoPago 3.pdf | L204: 47.99 | M204: 2026-07-166564228585 | N204: Unique transaction
A205: 2026-07 | B205: 46209 | C205: Pix enviado Bianca Mikaella Nascimento Lima | D205: 166642420855 | E205: -350 | F205: Outflow | G205: Person / External Transfer | H205: Sent Pix | I205: Bianca Mikaella Nascimento Lima | J205: 5620.69 | K205: MercadoPago 3.pdf | L205: 350 | M205: 2026-07-166642420855 | N205: Unique transaction
A206: 2026-07 | B206: 46209 | C206: Rendimentos | D206: 1746287484689 | E206: 8.34 | F206: Inflow | G206: Investment Yield | H206: Rendimentos | I206: Mercado Pago / Investment | J206: 10111.15 | K206: MercadoPago 3.pdf | L206: 8.34 | M206: 2026-07-1746287484689 | N206: Unique transaction
A207: 2026-07 | B207: 46210 | C207: Pagamento Mercado Libre | D207: 166747081089 | E207: -66.6 | F207: Outflow | G207: E-commerce | H207: Mercado Libre | J207: 5556.48 | K207: MercadoPago 3.pdf | L207: 66.6 | M207: 2026-07-166747081089 | N207: Unique transaction
A208: 2026-07 | B208: 46210 | C208: Pix enviado Gleudson Silva Farias | D208: 166801634625 | E208: -55 | F208: Outflow | G208: Person / External Transfer | H208: Sent Pix | I208: Gleudson Silva Farias | J208: 5501.48 | K208: MercadoPago 3.pdf | L208: 55 | M208: 2026-07-166801634625 | N208: Unique transaction
A209: 2026-07 | B209: 46210 | C209: Rendimentos | D209: 1746369624846 | E209: 2.39 | F209: Inflow | G209: Investment Yield | H209: Rendimentos | I209: Mercado Pago / Investment | J209: 5623.08 | K209: MercadoPago 3.pdf | L209: 2.39 | M209: 2026-07-1746369624846 | N209: Unique transaction
A210: 2026-07 | B210: 46211 | C210: Pix enviado Eva Bezerra da Silva Brandao | D210: 166972839363 | E210: -695 | F210: Outflow | G210: Person / External Transfer | H210: Sent Pix | I210: Eva Bezerra da Silva Brandao | J210: 4808.83 | K210: MercadoPago 3.pdf | L210: 695 | M210: 2026-07-166972839363 | N210: Unique transaction
A211: 2026-07 | B211: 46211 | C211: Rendimentos | D211: 1746440516625 | E211: 2.35 | F211: Inflow | G211: Investment Yield | H211: Rendimentos | I211: Mercado Pago / Investment | J211: 5503.83 | K211: MercadoPago 3.pdf | L211: 2.35 | M211: 2026-07-1746440516625 | N211: Unique transaction
A212: 2026-07 | B212: 46212 | C212: Pagamento com QR Pix ROMA VAREJO LTDA | D212: 167930404114 | E212: -9.19 | F212: Outflow | G212: Person / External Transfer | H212: Sent Pix | I212: ROMA VAREJO LTDA | J212: 4799.64 | K212: MercadoPago 3.pdf | L212: 9.19 | M212: 2026-07-167930404114 | N212: Unique transaction
A213: 2026-07 | B213: 46212 | C213: Rendimentos | D213: 1746508534022 | E213: 2.04 | F213: Inflow | G213: Investment Yield | H213: Rendimentos | I213: Mercado Pago / Investment | J213: 4801.68 | K213: MercadoPago 3.pdf | L213: 2.04 | M213: 2026-07-1746508534022 | N213: Unique transaction
A214: 2026-07 | B214: 46213 | C214: Pix enviado Estacao 89 Comercio Varejista de Alimentos Ltda | D214: 167316433679 | E214: -66.5 | F214: Outflow | G214: Groceries & Food | H214: Groceries / food | I214: Estacao 89 Comercio Varejista de Alimentos Ltda | J214: 4737.23 | K214: MercadoPago 3.pdf | L214: 66.5 | M214: 2026-07-167316433679 | N214: Unique transaction
A215: 2026-07 | B215: 46213 | C215: Rendimentos | D215: 1746544410775 | E215: 2.05 | F215: Inflow | G215: Investment Yield | H215: Rendimentos | I215: Mercado Pago / Investment | J215: 4803.73 | K215: MercadoPago 3.pdf | L215: 2.05 | M215: 2026-07-1746544410775 | N215: Unique transaction
A216: 2026-07 | B216: 46214 | C216: Pix enviado Marinaldo Domingos de Souza | D216: 168307215268 | E216: -450 | F216: Outflow | G216: Person / External Transfer | H216: Sent Pix | I216: Marinaldo Domingos de Souza | J216: 4287.23 | K216: MercadoPago 3.pdf | L216: 450 | M216: 2026-07-168307215268 | N216: Unique transaction
A217: 2026-07 | B217: 46215 | C217: MULTIDISPLAY COMERCIO E SERVICOS TECNOLOGICOS | D217: 167628441103 | E217: -25 | F217: Outflow | G217: Other | H217: Other | I217: MULTIDISPLAY COMERCIO E SERVICOS TECNOLOGICOS | J217: 4262.23 | K217: MercadoPago 3.pdf | L217: 25 | M217: 2026-07-167628441103 | N217: Unique transaction
A218: 2026-07 | B218: 46216 | C218: Pagamento de conta RENTAL PROJECTA SERVICOS E LOCACAO LTDA | D218: 168631780840 | E218: -413.11 | F218: Outflow | G218: Bills & Services | H218: Bill payment | I218: RENTAL PROJECTA SERVICOS E LOCACAO LTDA | J218: 3851.14 | K218: MercadoPago 3.pdf | L218: 413.11 | M218: 2026-07-168631780840 | N218: Unique transaction
A219: 2026-07 | B219: 46216 | C219: Pix enviado Estacao 89 Comercio Varejista de Alimentos Ltda | D219: 168671821000 | E219: -120.9 | F219: Outflow | G219: Groceries & Food | H219: Groceries / food | I219: Estacao 89 Comercio Varejista de Alimentos Ltda | J219: 3730.24 | K219: MercadoPago 3.pdf | L219: 120.9 | M219: 2026-07-168671821000 | N219: Unique transaction
... A228: 2026-07 | B228: 46221 | C228: Pagamento com QR Pix THALES JERONIMO DO NASCIMENTO SEIXAS | D228: 168610795753 | E228: -78 | F228: Outflow | G228: Person / External Transfer | H228: Sent Pix | I228: THALES JERONIMO DO NASCIMENTO SEIXAS | J228: 3106.72 | K228: MercadoPago 3.pdf | L228: 78 | M228: 2026-07-168610795753 | N228: Unique transaction
A229: 2026-07 | B229: 46222 | C229: Pagamento Mercado Livre | D229: 168727528099 | E229: -289.94 | F229: Outflow | G229: E-commerce | H229: Mercado Libre | J229: 2816.78 | K229: MercadoPago 3.pdf | L229: 289.94 | M229: 2026-07-168727528099 | N229: Unique transaction
A230: 2026-07 | B230: 46223 | C230: Pagamento GOOGLE BRASIL PAGAMENTOS LTDA. | D230: 169650573934 | E230: -96.99 | F230: Outflow | G230: Digital Services | H230: Google | I230: Pagamento GOOGLE BRASIL PAGAMENTOS LTDA. | J230: 2721.25 | K230: MercadoPago 3.pdf | L230: 96.99 | M230: 2026-07-169650573934 | N230: Unique transaction
A231: 2026-07 | B231: 46223 | C231: Rendimentos | D231: 1746956554470 | E231: 1.46 | F231: Inflow | G231: Investment Yield | H231: Rendimentos | I231: Mercado Pago / Investment | J231: 2818.24 | K231: MercadoPago 3.pdf | L231: 1.46 | M231: 2026-07-1746956554470 | N231: Unique transaction
...

Sheet Outflow Categories
A1: Outflow Categories
A2: Classification is analytical; transfers and credit-card settlements are separated from ordinary merchant consumption.
A4: Category | B4: Outflow Amount | C4: Share of Outflows | D4: Transaction Count
A5: Person / External Transfer | B5: 47343.84 | C5: 0.4131635 | D5: 89
A6: Credit Card Settlement | B6: 29540.63 | C6: 0.25779722 | D6: 5
A7: Bills & Services | B7: 9790.6 | C7: 0.085441287 | D7: 2
A8: Groceries & Food | B8: 6716.58 | C8: 0.058614716 | D8: 43
A9: E-commerce | B9: 4805.39 | C9: 0.041936011 | D9: 13
A10: Travel | B10: 3529.31 | C10: 0.030799827 | D10: 2
A11: Automotive | B11: 3340 | C11: 0.029147744 | D11: 2
A12: Purchases & Services | B12: 2096.13 | C12: 0.018292653 | D12: 8
A13: Dining | B13: 1448.9 | C13: 0.012644361 | D13: 12
A14: Taxes & Government | B14: 1342.74 | C14: 0.011717917 | D14: 1
A15: Utilities | B15: 1181.91 | C15: 0.010314374 | D15: 4
A16: Health | B16: 814.89 | C16: 0.0071114385 | D16: 5
... A24: Merchant Purchase | B24: 10 | C24: 8.7268693e-05 | D24: 1

Sheet Counterparties
A1: Counterparty Analysis
A2: Recurring names are aggregated across the five unique months.
A4: Counterparty | B4: Primary Category | C4: Transactions | D4: Net Amount | E4: Absolute Flow
B5: Credit Card Settlement | C5: 5 | D5: -29540.63 | E5: 29540.63
B6: E-commerce | C6: 13 | D6: -4805.39 | E6: 4805.39
A7: 52.875.146 VALDEBAM PROCOPIO DE ARAUJO | B7: Person / External Transfer | C7: 1 | D7: -73 | E7: 73
A8: 55.103.928 MARIA EDUARDA CARDOSO DA COSTA | B8: Person / External Transfer | C8: 1 | D8: -35 | E8: 35
A9: ATLANTICO SUL HOTELARIA E RESTAURANTES L | B9: Dining | C9: 1 | D9: -110 | E9: 110
A10: AUTO POSTO INTERMARES LTDA | B10: Fuel | C10: 1 | D10: -29.5 | E10: 29.5
A11: Amanda Gabrielle Freire De Souza | B11: Person / External Transfer | C11: 1 | D11: -131 | E11: 131
A12: B L SERVICE ADMINISTRADORA DE SERVICOS LTDA | B12: Person / External Transfer | C12: 1 | D12: -208 | E12: 208
A13: BANCO XP S.A | B13: Bills & Services | C13: 1 | D13: -9377.49 | E13: 9377.49
A14: BBP GASTRONOMIA LTDA | B14: Dining | C14: 1 | D14: -94.7 | E14: 94.7
A15: BUTIQUIM DO FORTAO LTDA | B15: Dining | C15: 3 | D15: -526.51 | E15: 526.51
A16: Bessa Express Loja De Proximidade Ltda | B16: Person / External Transfer | C16: 2 | D16: -69.45 | E16: 69.45
A17: Bianca Mikaella Nascimento Lima | B17: Person / External Transfer | C17: 5 | D17: -2570 | E17: 2570
A18: Br Brake Comercio e Servicos Automotivos Ltda | B18: Automotive | C18: 1 | D18: -3200 | E18: 3200
... A108: Williams Firmino dos Santos | B108: Person / External Transfer | C108: 1 | D108: -2085 | E108: 2085

Sheet Reconciliation
A1: Reconciliation & Source Control
A2: Statement totals are compared against the transaction ledger. Duplicate June source is documented but excluded.
A4: Source / Period | B4: Opening Balance | C4: Reported Inflows | D4: Calculated Inflows | E4: Inflows Variance | F4: Reported Outflows | G4: Calculated Outflows | H4: Outflows Variance | I4: Closing Balance | J4: Status
A5: April 2026 | B5: 21155.09 | C5: 27262.06 | D5: 27262.06 | E5: -3.6379788e-12 | F5: 21193.04 | G5: 21193.04 | H5: 0 | I5: 27224.11 | J5: PASS
A6: May 2026 | B6: 27224.11 | C6: 17065.63 | D6: 17065.63 | E6: -3.6379788e-12 | F6: 30217.29 | G6: 30217.29 | H6: 0 | I6: 14072.45 | J6: PASS
A7: June 2026 | B7: 14072.45 | C7: 24151.04 | D7: 24151.04 | E7: -3.6379788e-12 | F7: 14108.3 | G7: 14108.3 | H7: 0 | I7: 24115.19 | J7: PASS
A8: July 2026 | B8: 24115.19 | C8: 11272.89 | D8: 11272.89 | E8: 0 | F8: 31069.01 | G8: 31069.01 | H8: 3.6379788e-12 | I8: 4319.07 | J8: PASS
A9: August 2026 | B9: 4319.07 | C9: 25518.65 | D9: 25518.65 | E9: 0 | F9: 18000.99 | G9: 18000.99 | H9: -3.6379788e-12 | I9: 11836.73 | J9: PASS
A11: Source Register
A12: Source | B12: Period | C12: Role | D12: Workbook Treatment | E12: Transaction Detail
A13: MercadoPago.pdf | B13: June 2026 | C13: Unique month source | D13: Included | E13: 47 transactions
A14: MercadoPago 2.pdf | B14: August 2026 | C14: Unique month source | D14: Included | E14: 70 transactions
A15: MercadoPago 3.pdf | B15: July 2026 | C15: Unique month source | D15: Included | E15: 69 transactions
A16: MercadoPago 4.pdf | B16: June 2026 | C16: Duplicate of MercadoPago.pdf | D16: Excluded | E16: 0 added; duplicate
A17: User-supplied statement text | B17: May 2026 | C17: Statement content pasted in chat | D17: Included | E17: 76 transactions
A18: User-supplied statement text | B18: April 2026 | C18: Statement content pasted in chat | D18: Included | E18: 64 transactions

Sheet Analysis & Chat
A1: Analysis Log & Insights
A2: Condensed record of the analytical conclusions produced during the file-by-file review.
A4: Methodology
A5: • Applied the same procedure to each monthly statement: structure → data profile → inflows/outflows → liquidity trajectory → recurring counterparties → modeling distinctions → reconciliation.
A6: • Operation ID is retained as the transaction-level identifier.
A7: • Positive amounts are inflows; negative amounts are outflows; balance is the running balance.
A8: • Internal/self transfers are not automatically classified as income; credit-card settlements are not automatically treated as current-period consumption.
A10: April 2026
A11: • Opening R$21,155.09; inflows R$27,262.06; outflows R$21,193.04; closing R$27,224.11.
A12: • Dominant event: R$27,193.14 transfer received on Apr 30 after the balance fell to R$30.97.
A13: • Large Apr 9 outflows: R$3,235.00, R$3,200.00 and R$2,085.00.
A14: • Minimum observed balance: R$30.90. Reconciled.
... A52: • No transaction was fabricated to force reconciliation; the ledger is kept tied to supplied source data.
