Workbook

Sheet TOC & Legend
B2: [ REAL-TIME FINANCIAL MONITOR TERMINAL ]
B3: CLIENT: Eduardo Forster Giovannini | ACCT: 012026-082026 | VER: 4.0 Terminal
B5: STRUCTURED INDEX / APLICATIVOS DISPONÍVEIS
B6: Aba / Segmento | C6: Descrição & Escopo Funcional | D6: Acesso Direto (RT Links)
B7: TOC & Legend | C7: Apresentação do modelo, legenda de cores e controle de versão. | D7: =HYPERLINK("#'TOC & Legend'!A1", "GO TO TERMINAL →") -> GO TO TERMINAL →
B8: Dashboard & Comparisons | C8: Visão consolidada de saldos finais por cenário e gráfico comparativo. | D8: =HYPERLINK("#'Dashboard & Comparisons'!A1", "GO TO MONITOR →") -> GO TO MONITOR →
B9: Assumptions | C9: Configuração de premissas financeiras, custos fixos (sem o item loterias). | D9: =HYPERLINK("#'Assumptions'!A1", "GO TO SETTINGS →") -> GO TO SETTINGS →
B10: Detailed Cash Flow | C10: Demonstrativo detalhado mês a mês de todas as receitas e despesas sem Loterias. | D10: =HYPERLINK("#'Detailed Cash Flow'!A1", "GO TO DATABASE →") -> GO TO DATABASE →
B13: COLOR CODING & METRIC STATUS CODES
B14: INPUT | C14: Célula de Entrada | D14: Indica parâmetros e variáveis que o operador pode editar diretamente.
B15: CALCULATED | C15: Célula de Cálculo | D15: Indica valores consolidados gerados em tempo real por fórmulas analíticas.
B16: WARNING | C16: Aviso / Risco | D16: Alerta sobre riscos potenciais de double-counting (ex: Starlink, Cursor).
B17: TOTAL / TICKER | C17: Linha Consolidada | D17: Representa sumários de seções, médias acumuladas ou cabeçalhos principais.
B20: Terminal Mode Active | System Date: 2026-09-03 | Build 4.0.0-RT

Sheet Dashboard & Comparisons
B2: [ BBG SCENARIO ANALYSIS & RISK ENGINE ]
B3: Real-time projection of cash flow viability & bank balances by optimization model.
B5: SALDO ORIGINAL AGO/2026 | E5: SALDO SEM FILTRO AGO/2026 | H5: SALDO SANEADO AGO/2026
B6: =F14 -> 17836.73 | E6: =H14 -> 1336.73 | H6: =I14 -> 4336.73
B9: Mês / Referência | C9: Saldo Inicial | D9: Entradas Totais | E9: Saídas Históricas | F9: Saldo F. Original | G9: Saldo F. Cenário 1 (Doméstico) | H9: Saldo F. Cenário 2 (Sem Filtro) | I9: Saldo F. Otimizado (Sane Scenario)
B10: Abril 2026 | C10: =Assumptions!C6 -> 21155.09 | D10: ='Detailed Cash Flow'!C9 -> 27262.06 | E10: ='Detailed Cash Flow'!C14 -> 19993.04 | F10: =C10+D10-E10 -> 28424.11 | G10: =C10+D10-E10-'Detailed Cash Flow'!C19 -> 26174.11 | H10: =C10+D10-E10-'Detailed Cash Flow'!C28 -> 25124.11 | I10: =C10+D10-E10-'Detailed Cash Flow'!C38 -> 25724.11
B11: Maio 2026 | C11: =F10 -> 28424.11 | D11: ='Detailed Cash Flow'!D9 -> 17065.63 | E11: ='Detailed Cash Flow'!D14 -> 29017.29 | F11: =C11+D11-E11 -> 16472.45 | G11: =G10+D11-E11-'Detailed Cash Flow'!D19 -> 11972.45 | H11: =H10+D11-E11-'Detailed Cash Flow'!D28 -> 9872.45 | I11: =I10+D11-E11-'Detailed Cash Flow'!D38 -> 11072.45
B12: Junho 2026 | C12: =F11 -> 16472.45 | D12: ='Detailed Cash Flow'!E9 -> 24151.04 | E12: ='Detailed Cash Flow'!E14 -> 12908.3 | F12: =C12+D12-E12 -> 27715.19 | G12: =G11+D12-E12-'Detailed Cash Flow'!E19 -> 20965.19 | H12: =H11+D12-E12-'Detailed Cash Flow'!E28 -> 17815.19 | I12: =I11+D12-E12-'Detailed Cash Flow'!E38 -> 19615.19
B13: Julho 2026 | C13: =F12 -> 27715.19 | D13: ='Detailed Cash Flow'!F9 -> 11272.89 | E13: ='Detailed Cash Flow'!F14 -> 29869.01 | F13: =C13+D13-E13 -> 9119.07 | G13: =G12+D13-E13-'Detailed Cash Flow'!F19 -> 119.07 | H13: =H12+D13-E13-'Detailed Cash Flow'!F28 -> -4080.93 | I13: =I12+D13-E13-'Detailed Cash Flow'!F38 -> -1680.93
B14: Agosto 2026 | C14: =F13 -> 9119.07 | D14: ='Detailed Cash Flow'!G9 -> 25518.65 | E14: ='Detailed Cash Flow'!G14 -> 16800.99 | F14: =C14+D14-E14 -> 17836.73 | G14: =G13+D14-E14-'Detailed Cash Flow'!G19 -> 6586.73 | H14: =H13+D14-E14-'Detailed Cash Flow'!G28 -> 1336.73 | I14: =I13+D14-E14-'Detailed Cash Flow'!G38 -> 4336.73
B15: Saldo Final Médio | C15: - | D15: =AVERAGE(D10:D14) -> 21054.054 | E15: =AVERAGE(E10:E14) -> 21717.726 | F15: =AVERAGE(F10:F14) -> 19913.51 | G15: =AVERAGE(G10:G14) -> 13163.51 | H15: =AVERAGE(H10:H14) -> 10013.51 | I15: =AVERAGE(I10:I14) -> 11813.51
B17: VERIFICAÇÃO DE SAÚDE FINANCEIRA POR CENÁRIO:
B18: Original (Descontrolado) | C18: =IF(MIN(F10:F14)<0,"ALERTA: Conta Fica Negativa","OK: Saldo Positivo") -> OK: Saldo Positivo
B19: Cenário 1 (Com Gastos Domésticos) | C19: =IF(MIN(G10:G14)<0,"ALERTA: Conta Fica Negativa","OK: Saldo Positivo") -> OK: Saldo Positivo
B20: Cenário 2 (Com Duplicidades) | C20: =IF(MIN(H10:H14)<0,"ALERTA: Conta Fica Negativa","OK: Saldo Positivo") -> ALERTA: Conta Fica Negativa
B21: Cenário Saneado (Recomendado) | C21: =IF(MIN(I10:I14)<0,"ALERTA: Conta Fica Negativa","OK: Saldo Positivo") -> ALERTA: Conta Fica Negativa

Sheet Assumptions
B2: [ BBG TERMINAL - SYSTEM CONFIGURATOR ]
B3: Edit the cyan parameter values below to run real-time stress testing.
B5: 1. Saldo Inicial em Conta Corrente (Mercado Pago)
B6: Saldo Inicial (01/04/2026) | C6: 21155.09
B8: 2. Novos Gastos Adicionais Solicitados
B9: Item / Despesa | C9: Valor Mensal (R$) | D9: Observação / Detalhe
B10: Água (CAGEPA) | C10: 250 | D10: Novo custo fixo mensal estruturado para a casa.
B11: Luz (ENERGISA) | C11: 500 | D11: Estimativa de consumo elétrico mensal.
B12: Funcionário Doméstico | C12: 1500 | D12: Salário/encargos mensais de serviços gerais.
B13: Gasolina do Carro | C13: 600 | D13: Aumento real de R$ 465,03 frente à média histórica (R$ 134,97).
B14: STARLINK (Internet) | C14: 235 | D14: ⚠️ JÁ PAGO NO CARTÃO! Risco de duplicidade se somado fora.
B15: Google Pro | C15: 95 | D15: ⚠️ JÁ PAGO NO CARTÃO! Risco de duplicidade se somado fora.
B16: CURSOR IDE | C16: 120 | D16: ⚠️ JÁ PAGO NO CARTÃO! Risco de duplicidade se somado fora.
B18: 3. Regras de Saneamento & Otimização (Cenário Sane)
B19: Ação de Otimização | C19: Valor Proposto | D19: Impacto Mensal Estimado
B20: Remover Duplicidade Starlink | C20: R$ 0,00 extra | D20: Evita R$ 235,00/mês de lançamento fantasma
B21: Remover Duplicidade Cursor IDE | C21: R$ 0,00 extra | D21: Evita R$ 120,00/mês de lançamento fantasma
B22: Remover Duplicidade Google Pro | C22: R$ 0,00 extra | D22: Evita R$ 95,00/mês de lançamento fantasma
B23: Corte de Ferramentas IA Redundantes | C23: R$ 150,00 / mês | D23: Desativação de um dos modelos duplicados (ChatGPT ou Claude Pro)
B24: Eliminar Loterias Caixa Online | C24: R$ 0,00 / mês | D24: Economia total de R$ 1.200,00/mês (Item retirado do estudo!)

Sheet Detailed Cash Flow
B2: [ BBG REAL-TIME TRANSACTIONAL DATABASE ]
B3: Historical cash flows, new cost integrations and sane financial scenarios.
B5: Categoria / Fluxo | C5: Abril 2026 | D5: Maio 2026 | E5: Junho 2026 | F5: Julho 2026 | G5: Agosto 2026 | H5: Total Acumulado
B6: Receitas / Entradas (Histórico real)
B7: Transferências Recebidas (Pix/TED) | C7: 15949.17 | D7: 12693.31 | E7: 21971.04 | F7: 11000 | G7: 25299.17 | H7: =SUM(C7:G7) -> 86912.69
B8: Rendimento de Investimento (CDI MP) | C8: 11312.89 | D8: 4372.32 | E8: 2180 | F8: 272.89 | G8: 219.48 | H8: =SUM(C8:G8) -> 18357.58
B9: Total Inflows (A) | C9: =SUM(C7:C8) -> 27262.06 | D9: =SUM(D7:D8) -> 17065.63 | E9: =SUM(E7:E8) -> 24151.04 | F9: =SUM(F7:F8) -> 11272.89 | G9: =SUM(G7:G8) -> 25518.65 | H9: =SUM(C9:G9) -> 105270.27
B10: Despesas / Saídas (Histórico real SEM Loterias)
B11: Fatura de Cartão de Crédito | C11: 18527.22 | D11: 10350.03 | E11: 0 | F11: 13533.24 | G11: 3803.89 | H11: =SUM(C11:G11) -> 46214.38
B12: Transferências Realizadas (Pessoal/Pix) | C12: 1021.22 | D12: 10567.26 | E12: 4108.3 | F12: 7535.77 | G12: 14008.3 | H12: =SUM(C12:G12) -> 37240.85
B13: Outras Despesas e Tarifas | C13: 444.6 | D13: 8100 | E13: 8800 | F13: 8800 | G13: -1011.2 | H13: =SUM(C13:G13) -> 25133.4
B14: Total Outflows (B) - Histórico | C14: =SUM(C11:C13) -> 19993.04 | D14: =SUM(D11:D13) -> 29017.29 | E14: =SUM(E11:E13) -> 12908.3 | F14: =SUM(F11:F13) -> 29869.01 | G14: =SUM(G11:G13) -> 16800.99 | H14: =SUM(C14:G14) -> 108588.63
B15: CENÁRIO 1: GASTOS DOMÉSTICOS ADICIONAIS
B16: Água (CAGEPA) - Novo | C16: =Assumptions!$C$10 -> 250 | D16: =Assumptions!$C$10 -> 250 | E16: =Assumptions!$C$10 -> 250 | F16: =Assumptions!$C$10 -> 250 | G16: =Assumptions!$C$10 -> 250 | H16: =SUM(C16:G16) -> 1250
B17: Luz (ENERGISA) - Novo | C17: =Assumptions!$C$11 -> 500 | D17: =Assumptions!$C$11 -> 500 | E17: =Assumptions!$C$11 -> 500 | F17: =Assumptions!$C$11 -> 500 | G17: =Assumptions!$C$11 -> 500 | H17: =SUM(C17:G17) -> 2500
B18: Funcionário Doméstico - Novo | C18: =Assumptions!$C$12 -> 1500 | D18: =Assumptions!$C$12 -> 1500 | E18: =Assumptions!$C$12 -> 1500 | F18: =Assumptions!$C$12 -> 1500 | G18: =Assumptions!$C$12 -> 1500 | H18: =SUM(C18:G18) -> 7500
B19: Total Acréscimo - Cenário 1 (C) | C19: =SUM(C16:C18) -> 2250 | D19: =SUM(D16:D18) -> 2250 | E19: =SUM(E16:E18) -> 2250 | F19: =SUM(F16:F18) -> 2250 | G19: =SUM(G16:G18) -> 2250 | H19: =SUM(C19:G19) -> 11250
B20: CENÁRIO 2: TODOS OS GASTOS (SEM FILTRO / DUPLICADO)
B21: Água (CAGEPA) - Novo | C21: =Assumptions!$C$10 -> 250 | D21: =Assumptions!$C$10 -> 250 | E21: =Assumptions!$C$10 -> 250 | F21: =Assumptions!$C$10 -> 250 | G21: =Assumptions!$C$10 -> 250 | H21: =SUM(C21:G21) -> 1250
B22: Luz (ENERGISA) - Novo | C22: =Assumptions!$C$11 -> 500 | D22: =Assumptions!$C$11 -> 500 | E22: =Assumptions!$C$11 -> 500 | F22: =Assumptions!$C$11 -> 500 | G22: =Assumptions!$C$11 -> 500 | H22: =SUM(C22:G22) -> 2500
B23: Funcionário Doméstico - Novo | C23: =Assumptions!$C$12 -> 1500 | D23: =Assumptions!$C$12 -> 1500 | E23: =Assumptions!$C$12 -> 1500 | F23: =Assumptions!$C$12 -> 1500 | G23: =Assumptions!$C$12 -> 1500 | H23: =SUM(C23:G23) -> 7500
B24: Gasolina do Carro - Novo | C24: =Assumptions!$C$13 -> 600 | D24: =Assumptions!$C$13 -> 600 | E24: =Assumptions!$C$13 -> 600 | F24: =Assumptions!$C$13 -> 600 | G24: =Assumptions!$C$13 -> 600 | H24: =SUM(C24:G24) -> 3000
B25: STARLINK - Duplicado | C25: =Assumptions!$C$14 -> 235 | D25: =Assumptions!$C$14 -> 235 | E25: =Assumptions!$C$14 -> 235 | F25: =Assumptions!$C$14 -> 235 | G25: =Assumptions!$C$14 -> 235 | H25: =SUM(C25:G25) -> 1175
B26: Google Pro - Duplicado | C26: =Assumptions!$C$15 -> 95 | D26: =Assumptions!$C$15 -> 95 | E26: =Assumptions!$C$15 -> 95 | F26: =Assumptions!$C$15 -> 95 | G26: =Assumptions!$C$15 -> 95 | H26: =SUM(C26:G26) -> 475
B27: CURSOR IDE - Duplicado | C27: =Assumptions!$C$16 -> 120 | D27: =Assumptions!$C$16 -> 120 | E27: =Assumptions!$C$16 -> 120 | F27: =Assumptions!$C$16 -> 120 | G27: =Assumptions!$C$16 -> 120 | H27: =SUM(C27:G27) -> 600
B28: Total Acréscimo - Cenário 2 (D) | C28: =SUM(C21:C27) -> 3300 | D28: =SUM(D21:D27) -> 3300 | E28: =SUM(E21:E27) -> 3300 | F28: =SUM(F21:F27) -> 3300 | G28: =SUM(G21:G27) -> 3300 | H28: =SUM(C28:G28) -> 16500
B29: CENÁRIO 3: SANEADO / OTIMIZADO (SANE SCENARIO)
B30: Água (CAGEPA) - Novo | C30: =Assumptions!$C$10 -> 250 | D30: =Assumptions!$C$10 -> 250 | E30: =Assumptions!$C$10 -> 250 | F30: =Assumptions!$C$10 -> 250 | G30: =Assumptions!$C$10 -> 250 | H30: =SUM(C30:G30) -> 1250
B31: Luz (ENERGISA) - Novo | C31: =Assumptions!$C$11 -> 500 | D31: =Assumptions!$C$11 -> 500 | E31: =Assumptions!$C$11 -> 500 | F31: =Assumptions!$C$11 -> 500 | G31: =Assumptions!$C$11 -> 500 | H31: =SUM(C31:G31) -> 2500
B32: Funcionário Doméstico - Novo | C32: =Assumptions!$C$12 -> 1500 | D32: =Assumptions!$C$12 -> 1500 | E32: =Assumptions!$C$12 -> 1500 | F32: =Assumptions!$C$12 -> 1500 | G32: =Assumptions!$C$12 -> 1500 | H32: =SUM(C32:G32) -> 7500
B33: Gasolina do Carro - Novo | C33: =Assumptions!$C$13 -> 600 | D33: =Assumptions!$C$13 -> 600 | E33: =Assumptions!$C$13 -> 600 | F33: =Assumptions!$C$13 -> 600 | G33: =Assumptions!$C$13 -> 600 | H33: =SUM(C33:G33) -> 3000
B34: STARLINK - Otimizado (Já em Fatura) | C34: 0 | D34: 0 | E34: 0 | F34: 0 | G34: 0 | H34: =SUM(C34:G34) -> 0
B35: Google Pro - Otimizado (Já em Fatura) | C35: 0 | D35: 0 | E35: 0 | F35: 0 | G35: 0 | H35: =SUM(C35:G35) -> 0
B36: CURSOR IDE - Otimizado (Já em Fatura) | C36: 0 | D36: 0 | E36: 0 | F36: 0 | G36: 0 | H36: =SUM(C36:G36) -> 0
B37: Economia: Ferramentas IA Redundantes | C37: -150 | D37: -150 | E37: -150 | F37: -150 | G37: -150 | H37: =SUM(C37:G37) -> -750
B38: Total Diferença Líquida - Cenário Sane (E) | C38: =SUM(C30:C37) -> 2700 | D38: =SUM(D30:D37) -> 2700 | E38: =SUM(E30:E37) -> 2700 | F38: =SUM(F30:F37) -> 2700 | G38: =SUM(G30:G37) -> 2700 | H38: =SUM(C38:G38) -> 13500

Sheet Resumo Executivo
A1: RESUMO EXECUTIVO | FLUXO DE CAIXA E CENÁRIOS
A2: Leitura em menos de 5 minutos | Abril–Agosto de 2026
A4: HISTÓRIA EM 30 SEGUNDOS
A5: ="O modelo acompanha 5 meses de receitas, despesas e quatro trajetórias de saldo. No histórico, as saídas acumuladas superam as entradas em "&TEXT(ABS('Detailed Cash Flow'!H9-'Detailed Cash Flow'!H14),"R$ #,##0.00")&", mas o saldo original termina agosto positivo porque parte de "&TEXT(Assumptions!C6,"R$ #,##0.00")&". O risco está concentrado em julho: o cenário sem filtro e o saneado ficam negativos, enquanto o cenário doméstico mantém apenas uma margem mínima. Agosto recupera o caixa, porém o cenário saneado fecha com bem menos folga que o original." -> O modelo acompanha 5 meses de receitas, despesas e quatro trajetórias de saldo. No histórico, as saídas acumuladas superam as entradas em R$ 3318,36000, mas o saldo original termina agosto positivo porque parte de R$ 21155,09000. O risco está concentrado em julho: o cenário sem filtro e o saneado ficam negativos, enquanto o cenário doméstico mantém apenas uma margem mínima. Agosto recupera o caixa, porém o cenário saneado fecha com bem menos folga que o original.
A9: SALDO ORIGINAL | AGO | C9: SALDO SANEADO | AGO | E9: FLUXO HISTÓRICO ACUMULADO | G9: PIOR SALDO SANEADO
A10: ='Dashboard & Comparisons'!F14 -> 17836.73 | C10: ='Dashboard & Comparisons'!I14 -> 4336.73 | E10: ='Detailed Cash Flow'!H9-'Detailed Cash Flow'!H14 -> -3318.36 | G10: =MIN('Dashboard & Comparisons'!I10:I14) -> -1680.93
A11: Referência sem novos custos | C11: Após custos e otimizações | E11: Entradas menos saídas | G11: Ocorre em julho de 2026
A14: PRINCIPAIS TÓPICOS DO WORKBOOK
A16: TEMA | C16: O QUE O MODELO MOSTRA | F16: POR QUE IMPORTA
A17: Histórico real | C17: Entradas e saídas mensais reais, excluindo loterias. | F17: Base para avaliar a capacidade de sustentar novos custos.
A18: Novas premissas | C18: Água, luz, funcionário doméstico, gasolina e assinaturas. | F18: As entradas em Assumptions alimentam automaticamente os cenários.
A19: Comparação de cenários | C19: Original, doméstico, sem filtro/duplicidades e saneado. | F19: Mostra o impacto acumulado e o risco de saldo negativo.
A20: Saneamento | C20: Remove R$ 450/mês de duplicidades e corta R$ 150/mês em IA. | F20: Economiza R$ 600/mês versus o cenário sem filtro.
A23: AÇÕES RECOMENDADAS
A25: PRIORIDADE | B25: AÇÃO | F25: MOTIVO / RESULTADO ESPERADO
A26: 1 | B26: Evitar lançamentos duplicados de Starlink, Google Pro e Cursor. | F26: Protege R$ 450/mês já cobertos pela fatura do cartão.
A27: 2 | B27: Criar pelo menos R$ 1.680,93 de folga adicional antes de julho. | F27: É o déficit mínimo projetado no cenário saneado; uma margem maior reduz o risco operacional.
A28: 3 | B28: Revisar as saídas de julho e maio antes de assumir novos compromissos. | F28: Foram os meses de maior pressão: R$ 29.869,01 e R$ 29.017,29.
A29: 4 | B29: Investigar a queda do rendimento de investimento. | F29: Caiu de R$ 11.312,89 em abril para R$ 219,48 em agosto, reduzindo a sustentação das entradas.
A32: COMO USAR
A34: Edite apenas os valores de entrada em Assumptions (saldo inicial e custos mensais). Detailed Cash Flow e Dashboard & Comparisons recalculam os cenários; os indicadores desta aba também se atualizam automaticamente. O estudo exclui loterias e cobre somente abril a agosto de 2026.

Sheet Insights & Tendências
A1: INSIGHTS & TENDÊNCIAS | ABR–AGO 2026
A2: Comparação visual de saldos, volatilidade mensal e pontos de decisão
A4: ="O caixa não apresenta deterioração linear; ele alterna meses fortes e fracos. Julho concentra o maior risco, com fluxo histórico mensal de "&TEXT('Detailed Cash Flow'!F9-'Detailed Cash Flow'!F14,"R$ #,##0.00")&" e saldo saneado de "&TEXT('Dashboard & Comparisons'!I13,"R$ #,##0.00")&". A otimização melhora o cenário sem filtro em R$ 600/mês, mas ainda não elimina a insuficiência temporária de caixa." -> O caixa não apresenta deterioração linear; ele alterna meses fortes e fracos. Julho concentra o maior risco, com fluxo histórico mensal de -R$ 18596,12000 e saldo saneado de -R$ 1680,93000. A otimização melhora o cenário sem filtro em R$ 600/mês, mas ainda não elimina a insuficiência temporária de caixa.
A7: 1. TRAJETÓRIA DOS SALDOS FINAIS POR CENÁRIO
A8: Mês | B8: Original | C8: Doméstico | D8: Sem filtro | E8: Saneado
A9: ='Dashboard & Comparisons'!B10 -> Abril 2026 | B9: ='Dashboard & Comparisons'!F10 -> 28424.11 | C9: ='Dashboard & Comparisons'!G10 -> 26174.11 | D9: ='Dashboard & Comparisons'!H10 -> 25124.11 | E9: ='Dashboard & Comparisons'!I10 -> 25724.11
A10: ='Dashboard & Comparisons'!B11 -> Maio 2026 | B10: ='Dashboard & Comparisons'!F11 -> 16472.45 | C10: ='Dashboard & Comparisons'!G11 -> 11972.45 | D10: ='Dashboard & Comparisons'!H11 -> 9872.45 | E10: ='Dashboard & Comparisons'!I11 -> 11072.45
A11: ='Dashboard & Comparisons'!B12 -> Junho 2026 | B11: ='Dashboard & Comparisons'!F12 -> 27715.19 | C11: ='Dashboard & Comparisons'!G12 -> 20965.19 | D11: ='Dashboard & Comparisons'!H12 -> 17815.19 | E11: ='Dashboard & Comparisons'!I12 -> 19615.19
A12: ='Dashboard & Comparisons'!B13 -> Julho 2026 | B12: ='Dashboard & Comparisons'!F13 -> 9119.07 | C12: ='Dashboard & Comparisons'!G13 -> 119.07 | D12: ='Dashboard & Comparisons'!H13 -> -4080.93 | E12: ='Dashboard & Comparisons'!I13 -> -1680.93
A13: ='Dashboard & Comparisons'!B14 -> Agosto 2026 | B13: ='Dashboard & Comparisons'!F14 -> 17836.73 | C13: ='Dashboard & Comparisons'!G14 -> 6586.73 | D13: ='Dashboard & Comparisons'!H14 -> 1336.73 | E13: ='Dashboard & Comparisons'!I14 -> 4336.73
A32: 2. FLUXO LÍQUIDO HISTÓRICO MENSAL
A34: Mês | B34: Entradas - Saídas | C34: Leitura
A35: ='Dashboard & Comparisons'!B10 -> Abril 2026 | B35: ='Detailed Cash Flow'!C9-'Detailed Cash Flow'!C14 -> 7269.02 | C35: =IF(B35<0,"Déficit","Superávit") -> Superávit
A36: ='Dashboard & Comparisons'!B11 -> Maio 2026 | B36: ='Detailed Cash Flow'!D9-'Detailed Cash Flow'!D14 -> -11951.66 | C36: =IF(B36<0,"Déficit","Superávit") -> Déficit
A37: ='Dashboard & Comparisons'!B12 -> Junho 2026 | B37: ='Detailed Cash Flow'!E9-'Detailed Cash Flow'!E14 -> 11242.74 | C37: =IF(B37<0,"Déficit","Superávit") -> Superávit
A38: ='Dashboard & Comparisons'!B13 -> Julho 2026 | B38: ='Detailed Cash Flow'!F9-'Detailed Cash Flow'!F14 -> -18596.12 | C38: =IF(B38<0,"Déficit","Superávit") -> Déficit
A39: ='Dashboard & Comparisons'!B14 -> Agosto 2026 | B39: ='Detailed Cash Flow'!G9-'Detailed Cash Flow'!G14 -> 8717.66 | C39: =IF(B39<0,"Déficit","Superávit") -> Superávit
A59: 3. INSIGHTS QUE MERECEM ATENÇÃO
A60: INSIGHT | C60: EVIDÊNCIA | F60: IMPLICAÇÃO
A61: Julho é o ponto crítico | C61: Entradas de R$ 11.272,89 versus saídas de R$ 29.869,01. | F61: Planejar liquidez antes de julho é mais importante que olhar apenas o saldo final de agosto.
A62: A recuperação de agosto é real, mas frágil | C62: O saneado volta de -R$ 1.680,93 para R$ 4.336,73. | F62: Uma nova despesa extraordinária pode consumir rapidamente a folga.
A63: Rendimento perdeu relevância | C63: CDI cai 98,1% de abril a agosto. | F63: O fluxo depende cada vez mais das transferências recebidas.
A64: Otimizar evita desperdício, não resolve tudo | C64: Saneado melhora R$ 3.000 no acumulado versus sem filtro. | F64: Ainda é necessário buffer ou redução adicional para atravessar julho.
